setup.py
TracMgmtUtils.egg-info/PKG-INFO
TracMgmtUtils.egg-info/SOURCES.txt
TracMgmtUtils.egg-info/dependency_links.txt
TracMgmtUtils.egg-info/top_level.txt
trac_mgmt/__init__.py
trac_mgmt/trac-manager.py
trac_mgmt/trac_utils.py