Metadata-Version: 1.0
Name: TracMgmtUtils
Version: 1.1
Summary: Utility functions for managing Trac instances
Home-page: http://www.02strich.de
Author: Stefan Richter
Author-email: stefan@02strich.de
License: PSF
Platform: UNKNOWN
Classifier: Development Status :: 5 - Production/Stable
Classifier: Framework :: Trac
Classifier: Intended Audience :: Developers
Classifier: Intended Audience :: System Administrators
Classifier: License :: OSI Approved :: Python Software Foundation License
Classifier: Programming Language :: Python :: 2
